gsam/__init__.py
gsam/cli.py
gsam/core.py
gsam/components/__init__.py
gsam/components/collection.py
gsam/components/component.py
gsam/components/console.py
gsam/components/control.py
gsam/components/literal.py
gsam/components/loop.py
gsam/components/operator.py
gsam/internals/__init__.py
gsam/internals/ghost.py
gsam/internals/parser.py
gsam/internals/registry.py
gsam/models/__init__.py
gsam/models/base_node.py
gsam/models/node.py
gsam/models/node_signal.py
gsam/models/node_type.py
gsam-0.0.22.dist-info/METADATA
gsam-0.0.22.dist-info/WHEEL
gsam-0.0.22.dist-info/entry_points.txt
gsam-0.0.22.dist-info/top_level.txt
gsam-0.0.22.dist-info/RECORD
