Metadata-Version: 2.4
Name: gsam
Version: 0.0.22
Summary: A compiler for the GSAM language.
Home-page: https://github.com/AttAditya/gsam-compiler
Author: AttAditya
Requires-Python: >=3.8
Dynamic: author
Dynamic: description
Dynamic: description-content-type
Dynamic: home-page
Dynamic: requires-python
Dynamic: summary
